mcp_neo4j_aura_manager/__init__.py
mcp_neo4j_aura_manager/aura_api_client.py
mcp_neo4j_aura_manager/aura_manager.py
mcp_neo4j_aura_manager/server.py
mcp_neo4j_aura_manager/utils.py
mcp_neo4j_aura_manager-0.4.7.dist-info/METADATA
mcp_neo4j_aura_manager-0.4.7.dist-info/WHEEL
mcp_neo4j_aura_manager-0.4.7.dist-info/entry_points.txt
mcp_neo4j_aura_manager-0.4.7.dist-info/RECORD
