Metadata-Version: 2.4
Name: mcp-neo4j-aura-manager
Version: 0.4.7
Summary: MCP Neo4j Aura Database Instance Manager
Requires-Python: >=3.10
Requires-Dist: fastmcp>=2.0.0
Requires-Dist: requests>=2.31.0
Requires-Dist: starlette>=0.40.0
